PHASE/__init__.py
PHASE/dataset.py
PHASE/main.py
PHASE/modules.py
PHASE/utils.py
phase_dl-0.1.0.dist-info/LICENSE
phase_dl-0.1.0.dist-info/METADATA
phase_dl-0.1.0.dist-info/WHEEL
phase_dl-0.1.0.dist-info/entry_points.txt
phase_dl-0.1.0.dist-info/top_level.txt
phase_dl-0.1.0.dist-info/RECORD
